LICENSE.txt
MANIFEST.in
README.txt
setup.cfg
setup.py
initdotpy/__init__.py
initdotpy.egg-info/PKG-INFO
initdotpy.egg-info/SOURCES.txt
initdotpy.egg-info/dependency_links.txt
initdotpy.egg-info/top_level.txt
test/test_initdotpy.py